{
  "name": "eggapp",
  "version": "1.0.0",
  "description": "",
  "private": true,
  "egg": {
    "declarations": true
  },
  "dependencies": {
    "bcryptjs": "^2.4.3",
    "dotenv": "^16.3.1",
    "egg": "^3",
    "egg-email": "^1.0.2",
    "egg-jwt": "^3.1.7",
    "egg-mail": "^1.0.12",
    "egg-mongoose": "^3.3.1",
    "egg-scripts": "^2",
    "emailjs": "^4.0.2",
    "ioredis": "^5.3.2",
    "jsonwebtoken": "^9.0.1",
    "nodemailer": "^6.9.4"
  },
  "devDependencies": {
    "egg-bin": "^5",
    "egg-ci": "^2",
    "egg-mock": "^5",
    "eslint": "^8",
    "eslint-config-egg": "^12"
  },
  "engines": {
    "node": ">=16.0.0"
  },
  "scripts": {
    "start": "egg-scripts start  --title=egg-server-eggapp",
    "stop": "egg-scripts stop --title=egg-server-eggapp",
    "dev": "egg-bin dev",
    "debug": "egg-bin debug",
    "test": "npm run lint -- --fix && npm run test-local",
    "test-local": "egg-bin test",
    "cov": "egg-bin cov",
    "lint": "eslint .",
    "ci": "npm run lint && npm run cov"
  },
  "ci": {
    "version": "16, 18",
    "type": "github"
  },
  "repository": {
    "type": "git",
    "url": ""
  },
  "author": "",
  "license": "MIT"
}
